{
    "0":{
        "bus0":"DE0 0",
        "bus1":"DE0 13",
        "type":"Al\/St 240\/40 4-bundle 380.0",
        "x":22.7789775015,
        "r":2.7779240855,
        "g":0.0,
        "b":0.0038598276,
        "s_nom":5265.43,
        "s_nom_mod":0.0,
        "s_nom_extendable":true,
        "s_nom_min":5265.43,
        "s_nom_max":25265.43,
        "s_max_pu":0.7,
        "capital_cost":12092.636686187,
        "active":true,
        "build_year":2037,
        "lifetime":null,
        "length":287.1236935588,
        "carrier":"AC",
        "terrain_factor":1.0,
        "num_parallel":3.1007725703,
        "v_ang_min":null,
        "v_ang_max":null,
        "sub_network":"",
        "x_pu":0.0,
        "r_pu":0.0,
        "g_pu":0.0,
        "b_pu":0.0,
        "x_pu_eff":0.0001577492,
        "r_pu_eff":0.0000192377,
        "s_nom_opt":5265.4303081308,
        "dc":null,
        "i_nom":2.58,
        "v_nom":380.0,
        "id":"0",
        "location0":"DE0 0",
        "location1":"DE0 13",
        "location":null
    },
    "1":{
        "bus0":"DE0 0",
        "bus1":"DE0 17",
        "type":"Al\/St 240\/40 4-bundle 380.0",
        "x":16.9234272793,
        "r":2.063832595,
        "g":0.0,
        "b":0.0019836595,
        "s_nom":4379.3172618571,
        "s_nom_mod":0.0,
        "s_nom_extendable":true,
        "s_nom_min":4379.3172618571,
        "s_nom_max":24379.3172618571,
        "s_max_pu":0.7,
        "capital_cost":7470.7361923045,
        "active":true,
        "build_year":0,
        "lifetime":null,
        "length":177.417187994,
        "carrier":"AC",
        "terrain_factor":1.0,
        "num_parallel":2.5789473684,
        "v_ang_min":null,
        "v_ang_max":null,
        "sub_network":"",
        "x_pu":0.0,
        "r_pu":0.0,
        "g_pu":0.0,
        "b_pu":0.0,
        "x_pu_eff":0.0001171982,
        "r_pu_eff":0.0000142925,
        "s_nom_opt":4379.3173248063,
        "dc":0.0,
        "i_nom":2.58,
        "v_nom":380.0,
        "id":"1",
        "location0":"DE0 0",
        "location1":"DE0 17",
        "location":null
    },
    "10":{
        "bus0":"DE0 10",
        "bus1":"DE0 20",
        "type":"Al\/St 240\/40 4-bundle 380.0",
        "x":3.879498742,
        "r":0.4731096027,
        "g":0.0,
        "b":0.0029592543,
        "s_nom":11171.7277088193,
        "s_nom_mod":0.0,
        "s_nom_extendable":true,
        "s_nom_min":11171.7277088193,
        "s_nom_max":31171.7277088193,
        "s_max_pu":0.7,
        "capital_cost":4368.4274941536,
        "active":true,
        "build_year":0,
        "lifetime":null,
        "length":103.7521058518,
        "carrier":"AC",
        "terrain_factor":1.0,
        "num_parallel":6.5789473684,
        "v_ang_min":null,
        "v_ang_max":null,
        "sub_network":"",
        "x_pu":0.0,
        "r_pu":0.0,
        "g_pu":0.0,
        "b_pu":0.0,
        "x_pu_eff":0.0000268663,
        "r_pu_eff":0.0000032764,
        "s_nom_opt":11171.7287612663,
        "dc":0.0,
        "i_nom":2.58,
        "v_nom":380.0,
        "id":"10",
        "location0":"DE0 10",
        "location1":"DE0 20",
        "location":null
    },
    "11":{
        "bus0":"DE0 10",
        "bus1":"DE0 20",
        "type":"Al\/St 240\/40 4-bundle 380.0",
        "x":8.231180282,
        "r":1.0038024734,
        "g":0.0,
        "b":0.0013947481,
        "s_nom":5265.43,
        "s_nom_mod":0.0,
        "s_nom_extendable":true,
        "s_nom_min":5265.43,
        "s_nom_max":25265.43,
        "s_max_pu":0.7,
        "capital_cost":4368.3728034328,
        "active":true,
        "build_year":2037,
        "lifetime":null,
        "length":103.7521058518,
        "carrier":"AC",
        "terrain_factor":1.0,
        "num_parallel":3.1007725703,
        "v_ang_min":null,
        "v_ang_max":null,
        "sub_network":"",
        "x_pu":0.0,
        "r_pu":0.0,
        "g_pu":0.0,
        "b_pu":0.0,
        "x_pu_eff":0.0000570026,
        "r_pu_eff":0.0000069515,
        "s_nom_opt":5265.4300465883,
        "dc":null,
        "i_nom":2.58,
        "v_nom":380.0,
        "id":"11",
        "location0":"DE0 10",
        "location1":"DE0 20",
        "location":null
    },
    "12":{
        "bus0":"DE0 10",
        "bus1":"DE0 30",
        "type":"Al\/St 240\/40 4-bundle 380.0",
        "x":5.754978093,
        "r":0.7018265967,
        "g":0.0,
        "b":0.003651237,
        "s_nom":10188.6156704432,
        "s_nom_mod":0.0,
        "s_nom_extendable":true,
        "s_nom_min":10188.6156704432,
        "s_nom_max":30188.6156704432,
        "s_max_pu":0.7,
        "capital_cost":5911.6183833333,
        "active":true,
        "build_year":0,
        "lifetime":null,
        "length":140.3653193409,
        "carrier":"AC",
        "terrain_factor":1.0,
        "num_parallel":6.0,
        "v_ang_min":null,
        "v_ang_max":null,
        "sub_network":"",
        "x_pu":0.0,
        "r_pu":0.0,
        "g_pu":0.0,
        "b_pu":0.0,
        "x_pu_eff":0.0000398544,
        "r_pu_eff":0.0000048603,
        "s_nom_opt":10188.6159357684,
        "dc":0.0,
        "i_nom":2.58,
        "v_nom":380.0,
        "id":"12",
        "location0":"DE0 10",
        "location1":"DE0 30",
        "location":null
    },
    "13":{
        "bus0":"DE0 10",
        "bus1":"DE0 32",
        "type":"Al\/St 240\/40 4-bundle 380.0",
        "x":14.8802043537,
        "r":1.8146590675,
        "g":0.0,
        "b":0.0010489692,
        "s_nom":3396.2052234811,
        "s_nom_mod":0.0,
        "s_nom_extendable":true,
        "s_nom_min":3396.2052234811,
        "s_nom_max":23396.2052234811,
        "s_max_pu":0.7,
        "capital_cost":5094.3360050822,
        "active":true,
        "build_year":0,
        "lifetime":null,
        "length":120.9772711681,
        "carrier":"AC",
        "terrain_factor":1.0,
        "num_parallel":2.0,
        "v_ang_min":null,
        "v_ang_max":null,
        "sub_network":"",
        "x_pu":0.0,
        "r_pu":0.0,
        "g_pu":0.0,
        "b_pu":0.0,
        "x_pu_eff":0.0001030485,
        "r_pu_eff":0.0000125669,
        "s_nom_opt":3396.2052310493,
        "dc":0.0,
        "i_nom":2.58,
        "v_nom":380.0,
        "id":"13",
        "location0":"DE0 10",
        "location1":"DE0 32",
        "location":null
    },
    "14":{
        "bus0":"DE0 11",
        "bus1":"DE0 24",
        "type":"Al\/St 240\/40 4-bundle 380.0",
        "x":6.0065036703,
        "r":0.7325004476,
        "g":0.0,
        "b":0.0016936965,
        "s_nom":6792.4104469621,
        "s_nom_mod":0.0,
        "s_nom_extendable":true,
        "s_nom_min":6792.4104469621,
        "s_nom_max":26792.4104469621,
        "s_max_pu":0.7,
        "capital_cost":4112.3225124731,
        "active":true,
        "build_year":0,
        "lifetime":null,
        "length":97.6667263461,
        "carrier":"AC",
        "terrain_factor":1.0,
        "num_parallel":4.0,
        "v_ang_min":null,
        "v_ang_max":null,
        "sub_network":"",
        "x_pu":0.0,
        "r_pu":0.0,
        "g_pu":0.0,
        "b_pu":0.0,
        "x_pu_eff":0.0000415963,
        "r_pu_eff":0.0000050727,
        "s_nom_opt":6792.4105606927,
        "dc":0.0,
        "i_nom":2.58,
        "v_nom":380.0,
        "id":"14",
        "location0":"DE0 11",
        "location1":"DE0 24",
        "location":null
    },
    "15":{
        "bus0":"DE0 11",
        "bus1":"DE0 25",
        "type":"Al\/St 240\/40 4-bundle 380.0",
        "x":5.7582276553,
        "r":0.7022228848,
        "g":0.0,
        "b":0.0021277176,
        "s_nom":7775.5224853382,
        "s_nom_mod":0.0,
        "s_nom_extendable":true,
        "s_nom_min":7775.5224853382,
        "s_nom_max":27775.5224853382,
        "s_max_pu":0.7,
        "capital_cost":4513.7195580373,
        "active":true,
        "build_year":0,
        "lifetime":null,
        "length":107.1813876788,
        "carrier":"AC",
        "terrain_factor":1.0,
        "num_parallel":4.5789473684,
        "v_ang_min":null,
        "v_ang_max":null,
        "sub_network":"",
        "x_pu":0.0,
        "r_pu":0.0,
        "g_pu":0.0,
        "b_pu":0.0,
        "x_pu_eff":0.0000398769,
        "r_pu_eff":0.000004863,
        "s_nom_opt":7775.5226866593,
        "dc":0.0,
        "i_nom":2.58,
        "v_nom":380.0,
        "id":"15",
        "location0":"DE0 11",
        "location1":"DE0 25",
        "location":null
    },
    "16":{
        "bus0":"DE0 11",
        "bus1":"DE0 28",
        "type":"Al\/St 240\/40 4-bundle 380.0",
        "x":19.3088289503,
        "r":2.3547352378,
        "g":0.0,
        "b":0.0013611619,
        "s_nom":3396.2052234811,
        "s_nom_mod":0.0,
        "s_nom_extendable":true,
        "s_nom_min":3396.2052234811,
        "s_nom_max":23396.2052234811,
        "s_max_pu":0.7,
        "capital_cost":6610.2409326307,
        "active":true,
        "build_year":0,
        "lifetime":null,
        "length":156.9823491891,
        "carrier":"AC",
        "terrain_factor":1.0,
        "num_parallel":2.0,
        "v_ang_min":null,
        "v_ang_max":null,
        "sub_network":"",
        "x_pu":0.0,
        "r_pu":0.0,
        "g_pu":0.0,
        "b_pu":0.0,
        "x_pu_eff":0.0001337177,
        "r_pu_eff":0.000016307,
        "s_nom_opt":3396.2052773186,
        "dc":0.0,
        "i_nom":2.58,
        "v_nom":380.0,
        "id":"16",
        "location0":"DE0 11",
        "location1":"DE0 28",
        "location":null
    },
    "17":{
        "bus0":"DE0 11",
        "bus1":"DE0 34",
        "type":"Al\/St 240\/40 4-bundle 380.0",
        "x":9.0342018212,
        "r":1.1017319294,
        "g":0.0,
        "b":0.0013099944,
        "s_nom":4870.8732810452,
        "s_nom_mod":0.0,
        "s_nom_extendable":true,
        "s_nom_min":4870.8732810452,
        "s_nom_max":24870.8732810452,
        "s_max_pu":0.7,
        "capital_cost":4435.0506909926,
        "active":true,
        "build_year":0,
        "lifetime":null,
        "length":105.3410353561,
        "carrier":"AC",
        "terrain_factor":1.0,
        "num_parallel":2.8684210526,
        "v_ang_min":null,
        "v_ang_max":null,
        "sub_network":"",
        "x_pu":0.0,
        "r_pu":0.0,
        "g_pu":0.0,
        "b_pu":0.0,
        "x_pu_eff":0.0000625637,
        "r_pu_eff":0.0000076297,
        "s_nom_opt":4870.8733267385,
        "dc":0.0,
        "i_nom":2.58,
        "v_nom":380.0,
        "id":"17",
        "location0":"DE0 11",
        "location1":"DE0 34",
        "location":null
    },
    "18":{
        "bus0":"DE0 12",
        "bus1":"DE0 14",
        "type":"Al\/St 240\/40 4-bundle 380.0",
        "x":16.294044934,
        "r":1.9870786505,
        "g":0.0,
        "b":0.0023626999,
        "s_nom":4870.8732810452,
        "s_nom_mod":0.0,
        "s_nom_extendable":true,
        "s_nom_min":4870.8732810452,
        "s_nom_max":24870.8732810452,
        "s_max_pu":0.7,
        "capital_cost":7999.1150359355,
        "active":true,
        "build_year":0,
        "lifetime":null,
        "length":189.9926078102,
        "carrier":"AC",
        "terrain_factor":1.0,
        "num_parallel":2.8684210526,
        "v_ang_min":null,
        "v_ang_max":null,
        "sub_network":"",
        "x_pu":0.0,
        "r_pu":0.0,
        "g_pu":0.0,
        "b_pu":0.0,
        "x_pu_eff":0.0001128396,
        "r_pu_eff":0.0000137609,
        "s_nom_opt":4870.8733956691,
        "dc":0.0,
        "i_nom":2.58,
        "v_nom":380.0,
        "id":"18",
        "location0":"DE0 12",
        "location1":"DE0 14",
        "location":null
    },
    "19":{
        "bus0":"DE0 12",
        "bus1":"DE0 25",
        "type":"Al\/St 240\/40 4-bundle 380.0",
        "x":6.8806052985,
        "r":0.8390982071,
        "g":0.0,
        "b":0.0015532134,
        "s_nom":6077.4198735977,
        "s_nom_mod":0.0,
        "s_nom_extendable":true,
        "s_nom_min":6077.4198735977,
        "s_nom_max":26077.4198735977,
        "s_max_pu":0.7,
        "capital_cost":4214.6320235383,
        "active":true,
        "build_year":0,
        "lifetime":null,
        "length":100.1029440092,
        "carrier":"AC",
        "terrain_factor":1.0,
        "num_parallel":3.5789473684,
        "v_ang_min":null,
        "v_ang_max":null,
        "sub_network":"",
        "x_pu":0.0,
        "r_pu":0.0,
        "g_pu":0.0,
        "b_pu":0.0,
        "x_pu_eff":0.0000476496,
        "r_pu_eff":0.0000058109,
        "s_nom_opt":6077.419932401,
        "dc":0.0,
        "i_nom":2.58,
        "v_nom":380.0,
        "id":"19",
        "location0":"DE0 12",
        "location1":"DE0 25",
        "location":null
    },
    "2":{
        "bus0":"DE0 0",
        "bus1":"DE0 32",
        "type":"Al\/St 240\/40 4-bundle 380.0",
        "x":7.7110997126,
        "r":0.9403780137,
        "g":0.0,
        "b":0.0025004501,
        "s_nom":7283.9664661502,
        "s_nom_mod":0.0,
        "s_nom_extendable":true,
        "s_nom_min":7283.9664661502,
        "s_nom_max":27283.9664661502,
        "s_max_pu":0.7,
        "capital_cost":5660.3665594628,
        "active":true,
        "build_year":0,
        "lifetime":null,
        "length":134.4575581044,
        "carrier":"AC",
        "terrain_factor":1.0,
        "num_parallel":4.2894736842,
        "v_ang_min":null,
        "v_ang_max":null,
        "sub_network":"",
        "x_pu":0.0,
        "r_pu":0.0,
        "g_pu":0.0,
        "b_pu":0.0,
        "x_pu_eff":0.000053401,
        "r_pu_eff":0.0000065123,
        "s_nom_opt":7283.966549297,
        "dc":0.0,
        "i_nom":2.58,
        "v_nom":380.0,
        "id":"2",
        "location0":"DE0 0",
        "location1":"DE0 32",
        "location":null
    },
    "20":{
        "bus0":"DE0 12",
        "bus1":"DE0 3",
        "type":"Al\/St 240\/40 4-bundle 380.0",
        "x":87.9797507238,
        "r":10.7292378931,
        "g":0.0,
        "b":0.0001299256,
        "s_nom":491.556019188,
        "s_nom_mod":0.0,
        "s_nom_extendable":true,
        "s_nom_min":491.556019188,
        "s_nom_max":20491.556019188,
        "s_max_pu":0.7,
        "capital_cost":4358.7857348702,
        "active":true,
        "build_year":0,
        "lifetime":null,
        "length":103.5277340566,
        "carrier":"AC",
        "terrain_factor":1.0,
        "num_parallel":0.2894736842,
        "v_ang_min":null,
        "v_ang_max":null,
        "sub_network":"",
        "x_pu":0.0,
        "r_pu":0.0,
        "g_pu":0.0,
        "b_pu":0.0,
        "x_pu_eff":0.0006092781,
        "r_pu_eff":0.0000743022,
        "s_nom_opt":491.5560215738,
        "dc":0.0,
        "i_nom":2.58,
        "v_nom":380.0,
        "id":"20",
        "location0":"DE0 12",
        "location1":"DE0 3",
        "location":null
    },
    "21":{
        "bus0":"DE0 12",
        "bus1":"DE0 38",
        "type":"Al\/St 240\/40 4-bundle 380.0",
        "x":5.6273924238,
        "r":0.6862673688,
        "g":0.0,
        "b":0.0015867958,
        "s_nom":6792.4104469621,
        "s_nom_mod":0.0,
        "s_nom_extendable":true,
        "s_nom_min":6792.4104469621,
        "s_nom_max":26792.4104469621,
        "s_max_pu":0.7,
        "capital_cost":3853.1350953932,
        "active":true,
        "build_year":0,
        "lifetime":null,
        "length":91.5023158338,
        "carrier":"AC",
        "terrain_factor":1.0,
        "num_parallel":4.0,
        "v_ang_min":null,
        "v_ang_max":null,
        "sub_network":"",
        "x_pu":0.0,
        "r_pu":0.0,
        "g_pu":0.0,
        "b_pu":0.0,
        "x_pu_eff":0.0000389709,
        "r_pu_eff":0.0000047525,
        "s_nom_opt":6792.4104979281,
        "dc":0.0,
        "i_nom":2.58,
        "v_nom":380.0,
        "id":"21",
        "location0":"DE0 12",
        "location1":"DE0 38",
        "location":null
    },
    "22":{
        "bus0":"DE0 12",
        "bus1":"DE0 9",
        "type":"Al\/St 240\/40 4-bundle 380.0",
        "x":14.8878688191,
        "r":1.8155937584,
        "g":0.0,
        "b":0.0025227035,
        "s_nom":5265.43,
        "s_nom_mod":0.0,
        "s_nom_extendable":true,
        "s_nom_min":5265.43,
        "s_nom_max":25265.43,
        "s_max_pu":0.7,
        "capital_cost":7902.7599549286,
        "active":true,
        "build_year":2037,
        "lifetime":null,
        "length":187.6581108294,
        "carrier":"AC",
        "terrain_factor":1.0,
        "num_parallel":3.1007725703,
        "v_ang_min":null,
        "v_ang_max":null,
        "sub_network":"",
        "x_pu":0.0,
        "r_pu":0.0,
        "g_pu":0.0,
        "b_pu":0.0,
        "x_pu_eff":0.0001031016,
        "r_pu_eff":0.0000125734,
        "s_nom_opt":5265.4300670925,
        "dc":null,
        "i_nom":2.58,
        "v_nom":380.0,
        "id":"22",
        "location0":"DE0 12",
        "location1":"DE0 9",
        "location":null
    },
    "23":{
        "bus0":"DE0 13",
        "bus1":"DE0 17",
        "type":"Al\/St 240\/40 4-bundle 380.0",
        "x":33.7565379134,
        "r":4.116650965,
        "g":0.0,
        "b":0.0009891832,
        "s_nom":2189.6586309286,
        "s_nom_mod":0.0,
        "s_nom_extendable":true,
        "s_nom_min":2189.6586309286,
        "s_nom_max":22189.6586309286,
        "s_max_pu":0.7,
        "capital_cost":7449.2870971852,
        "active":true,
        "build_year":0,
        "lifetime":null,
        "length":176.9437695503,
        "carrier":"AC",
        "terrain_factor":1.0,
        "num_parallel":1.2894736842,
        "v_ang_min":null,
        "v_ang_max":null,
        "sub_network":"",
        "x_pu":0.0,
        "r_pu":0.0,
        "g_pu":0.0,
        "b_pu":0.0,
        "x_pu_eff":0.000233771,
        "r_pu_eff":0.0000285087,
        "s_nom_opt":2189.6587046019,
        "dc":0.0,
        "i_nom":2.58,
        "v_nom":380.0,
        "id":"23",
        "location0":"DE0 13",
        "location1":"DE0 17",
        "location":null
    },
    "24":{
        "bus0":"DE0 13",
        "bus1":"DE0 19",
        "type":"Al\/St 240\/40 4-bundle 380.0",
        "x":15.8849097092,
        "r":1.9371841109,
        "g":0.0,
        "b":0.0011197952,
        "s_nom":3396.2052234811,
        "s_nom_mod":0.0,
        "s_nom_extendable":true,
        "s_nom_min":3396.2052234811,
        "s_nom_max":23396.2052234811,
        "s_max_pu":0.7,
        "capital_cost":5439.2150323395,
        "active":true,
        "build_year":0,
        "lifetime":null,
        "length":129.1456073917,
        "carrier":"AC",
        "terrain_factor":1.0,
        "num_parallel":2.0,
        "v_ang_min":null,
        "v_ang_max":null,
        "sub_network":"",
        "x_pu":0.0,
        "r_pu":0.0,
        "g_pu":0.0,
        "b_pu":0.0,
        "x_pu_eff":0.0001100063,
        "r_pu_eff":0.0000134154,
        "s_nom_opt":3396.2052688702,
        "dc":0.0,
        "i_nom":2.58,
        "v_nom":380.0,
        "id":"24",
        "location0":"DE0 13",
        "location1":"DE0 19",
        "location":null
    },
    "25":{
        "bus0":"DE0 13",
        "bus1":"DE0 23",
        "type":"Al\/St 240\/40 4-bundle 380.0",
        "x":52.7141652806,
        "r":6.4285567415,
        "g":0.0,
        "b":0.0003113862,
        "s_nom":983.1120383761,
        "s_nom_mod":0.0,
        "s_nom_extendable":true,
        "s_nom_min":983.1120383761,
        "s_nom_max":20983.1120383761,
        "s_max_pu":0.7,
        "capital_cost":5223.8196669961,
        "active":true,
        "build_year":0,
        "lifetime":null,
        "length":124.059866942,
        "carrier":"AC",
        "terrain_factor":1.0,
        "num_parallel":0.5789473684,
        "v_ang_min":null,
        "v_ang_max":null,
        "sub_network":"",
        "x_pu":0.0,
        "r_pu":0.0,
        "g_pu":0.0,
        "b_pu":0.0,
        "x_pu_eff":0.0003650565,
        "r_pu_eff":0.0000445191,
        "s_nom_opt":983.1120880689,
        "dc":0.0,
        "i_nom":2.58,
        "v_nom":380.0,
        "id":"25",
        "location0":"DE0 13",
        "location1":"DE0 23",
        "location":null
    },
    "26":{
        "bus0":"DE0 13",
        "bus1":"DE0 32",
        "type":"Al\/St 240\/40 4-bundle 380.0",
        "x":19.0729327925,
        "r":2.3259674137,
        "g":0.0,
        "b":0.0022356113,
        "s_nom":4379.3172618571,
        "s_nom_mod":0.0,
        "s_nom_extendable":true,
        "s_nom_min":4379.3172618571,
        "s_nom_max":24379.3172618571,
        "s_max_pu":0.7,
        "capital_cost":8417.7054805507,
        "active":true,
        "build_year":0,
        "lifetime":null,
        "length":199.9515846879,
        "carrier":"AC",
        "terrain_factor":1.0,
        "num_parallel":2.5789473684,
        "v_ang_min":null,
        "v_ang_max":null,
        "sub_network":"",
        "x_pu":0.0,
        "r_pu":0.0,
        "g_pu":0.0,
        "b_pu":0.0,
        "x_pu_eff":0.000132084,
        "r_pu_eff":0.0000161078,
        "s_nom_opt":4379.3173678172,
        "dc":0.0,
        "i_nom":2.58,
        "v_nom":380.0,
        "id":"26",
        "location0":"DE0 13",
        "location1":"DE0 32",
        "location":null
    },
    "27":{
        "bus0":"DE0 13",
        "bus1":"DE0 33",
        "type":"Al\/St 240\/40 4-bundle 380.0",
        "x":23.7921192968,
        "r":2.901477963,
        "g":0.0,
        "b":0.0016772082,
        "s_nom":3396.2052234811,
        "s_nom_mod":0.0,
        "s_nom_extendable":true,
        "s_nom_min":3396.2052234811,
        "s_nom_max":23396.2052234811,
        "s_max_pu":0.7,
        "capital_cost":8146.6292384609,
        "active":true,
        "build_year":0,
        "lifetime":null,
        "length":193.4318642012,
        "carrier":"AC",
        "terrain_factor":1.0,
        "num_parallel":2.0,
        "v_ang_min":null,
        "v_ang_max":null,
        "sub_network":"",
        "x_pu":0.0,
        "r_pu":0.0,
        "g_pu":0.0,
        "b_pu":0.0,
        "x_pu_eff":0.0001647654,
        "r_pu_eff":0.0000200933,
        "s_nom_opt":3396.2052354621,
        "dc":0.0,
        "i_nom":2.58,
        "v_nom":380.0,
        "id":"27",
        "location0":"DE0 13",
        "location1":"DE0 33",
        "location":null
    },
    "28":{
        "bus0":"DE0 13",
        "bus1":"DE0 36",
        "type":"Al\/St 240\/40 4-bundle 380.0",
        "x":8.9276328926,
        "r":1.0887357186,
        "g":0.0,
        "b":0.002517388,
        "s_nom":6792.4104469621,
        "s_nom_mod":0.0,
        "s_nom_extendable":true,
        "s_nom_min":6792.4104469621,
        "s_nom_max":26792.4104469621,
        "s_max_pu":0.7,
        "capital_cost":6111.8585128978,
        "active":true,
        "build_year":0,
        "lifetime":null,
        "length":145.1647624815,
        "carrier":"AC",
        "terrain_factor":1.0,
        "num_parallel":4.0,
        "v_ang_min":null,
        "v_ang_max":null,
        "sub_network":"",
        "x_pu":0.0,
        "r_pu":0.0,
        "g_pu":0.0,
        "b_pu":0.0,
        "x_pu_eff":0.0000618257,
        "r_pu_eff":0.0000075397,
        "s_nom_opt":6792.4105228809,
        "dc":0.0,
        "i_nom":2.58,
        "v_nom":380.0,
        "id":"28",
        "location0":"DE0 13",
        "location1":"DE0 36",
        "location":null
    },
    "29":{
        "bus0":"DE0 13",
        "bus1":"DE0 6",
        "type":"Al\/St 240\/40 4-bundle 380.0",
        "x":73.1704649765,
        "r":8.9232274362,
        "g":0.0,
        "b":0.000432223,
        "s_nom":983.1120383761,
        "s_nom_mod":0.0,
        "s_nom_extendable":true,
        "s_nom_min":983.1120383761,
        "s_nom_max":20983.1120383761,
        "s_max_pu":0.7,
        "capital_cost":7250.3625490109,
        "active":true,
        "build_year":0,
        "lifetime":null,
        "length":172.2026347329,
        "carrier":"AC",
        "terrain_factor":1.0,
        "num_parallel":0.5789473684,
        "v_ang_min":null,
        "v_ang_max":null,
        "sub_network":"",
        "x_pu":0.0,
        "r_pu":0.0,
        "g_pu":0.0,
        "b_pu":0.0,
        "x_pu_eff":0.0005067207,
        "r_pu_eff":0.0000617952,
        "s_nom_opt":983.1120622237,
        "dc":0.0,
        "i_nom":2.58,
        "v_nom":380.0,
        "id":"29",
        "location0":"DE0 13",
        "location1":"DE0 6",
        "location":null
    },
    "3":{
        "bus0":"DE0 1",
        "bus1":"DE0 18",
        "type":"Al\/St 240\/40 4-bundle 380.0",
        "x":9.483794311,
        "r":1.1565602818,
        "g":0.0,
        "b":0.0006685532,
        "s_nom":3396.2052234811,
        "s_nom_mod":0.0,
        "s_nom_extendable":true,
        "s_nom_min":3396.2052234811,
        "s_nom_max":23396.2052234811,
        "s_max_pu":0.7,
        "capital_cost":3246.5927495732,
        "active":true,
        "build_year":0,
        "lifetime":null,
        "length":77.1040187887,
        "carrier":"AC",
        "terrain_factor":1.0,
        "num_parallel":2.0,
        "v_ang_min":null,
        "v_ang_max":null,
        "sub_network":"",
        "x_pu":0.0,
        "r_pu":0.0,
        "g_pu":0.0,
        "b_pu":0.0,
        "x_pu_eff":0.0000656772,
        "r_pu_eff":0.0000080094,
        "s_nom_opt":3396.2052272125,
        "dc":0.0,
        "i_nom":2.58,
        "v_nom":380.0,
        "id":"3",
        "location0":"DE0 1",
        "location1":"DE0 18",
        "location":null
    },
    "30":{
        "bus0":"DE0 14",
        "bus1":"DE0 21",
        "type":"Al\/St 240\/40 4-bundle 380.0",
        "x":8.6509396916,
        "r":1.0549926453,
        "g":0.0,
        "b":0.0010140097,
        "s_nom":4379.3172618571,
        "s_nom_mod":0.0,
        "s_nom_extendable":true,
        "s_nom_min":4379.3172618571,
        "s_nom_max":24379.3172618571,
        "s_max_pu":0.7,
        "capital_cost":3818.5071871959,
        "active":true,
        "build_year":0,
        "lifetime":null,
        "length":90.6923502111,
        "carrier":"AC",
        "terrain_factor":1.0,
        "num_parallel":2.5789473684,
        "v_ang_min":null,
        "v_ang_max":null,
        "sub_network":"",
        "x_pu":0.0,
        "r_pu":0.0,
        "g_pu":0.0,
        "b_pu":0.0,
        "x_pu_eff":0.0000599096,
        "r_pu_eff":0.000007306,
        "s_nom_opt":4379.3172887888,
        "dc":0.0,
        "i_nom":2.58,
        "v_nom":380.0,
        "id":"30",
        "location0":"DE0 14",
        "location1":"DE0 21",
        "location":null
    },
    "31":{
        "bus0":"DE0 14",
        "bus1":"DE0 22",
        "type":"Al\/St 240\/40 4-bundle 380.0",
        "x":10.7950992483,
        "r":1.3164755181,
        "g":0.0,
        "b":0.0012653348,
        "s_nom":4379.3172618571,
        "s_nom_mod":0.0,
        "s_nom_extendable":true,
        "s_nom_min":4379.3172618571,
        "s_nom_max":24379.3172618571,
        "s_max_pu":0.7,
        "capital_cost":4764.6028255001,
        "active":true,
        "build_year":0,
        "lifetime":null,
        "length":113.1707024321,
        "carrier":"AC",
        "terrain_factor":1.0,
        "num_parallel":2.5789473684,
        "v_ang_min":null,
        "v_ang_max":null,
        "sub_network":"",
        "x_pu":0.0,
        "r_pu":0.0,
        "g_pu":0.0,
        "b_pu":0.0,
        "x_pu_eff":0.0000747583,
        "r_pu_eff":0.0000091169,
        "s_nom_opt":4379.3173236401,
        "dc":0.0,
        "i_nom":2.58,
        "v_nom":380.0,
        "id":"31",
        "location0":"DE0 14",
        "location1":"DE0 22",
        "location":null
    },
    "32":{
        "bus0":"DE0 15",
        "bus1":"DE0 24",
        "type":"Al\/St 240\/40 4-bundle 380.0",
        "x":10.6043002565,
        "r":1.2932073484,
        "g":0.0,
        "b":0.0012429705,
        "s_nom":4379.3172618571,
        "s_nom_mod":0.0,
        "s_nom_extendable":true,
        "s_nom_min":4379.3172618571,
        "s_nom_max":24379.3172618571,
        "s_max_pu":0.7,
        "capital_cost":4680.2780151937,
        "active":true,
        "build_year":0,
        "lifetime":null,
        "length":111.1704562619,
        "carrier":"AC",
        "terrain_factor":1.0,
        "num_parallel":2.5789473684,
        "v_ang_min":null,
        "v_ang_max":null,
        "sub_network":"",
        "x_pu":0.0,
        "r_pu":0.0,
        "g_pu":0.0,
        "b_pu":0.0,
        "x_pu_eff":0.000073437,
        "r_pu_eff":0.0000089557,
        "s_nom_opt":4379.3172652559,
        "dc":0.0,
        "i_nom":2.58,
        "v_nom":380.0,
        "id":"32",
        "location0":"DE0 15",
        "location1":"DE0 24",
        "location":null
    },
    "33":{
        "bus0":"DE0 15",
        "bus1":"DE0 26",
        "type":"Al\/St 240\/40 4-bundle 380.0",
        "x":6.2157792534,
        "r":0.7580218602,
        "g":0.0,
        "b":0.0022967871,
        "s_nom":7775.5224853382,
        "s_nom_mod":0.0,
        "s_nom_extendable":true,
        "s_nom_min":7775.5224853382,
        "s_nom_max":27775.5224853382,
        "s_max_pu":0.7,
        "capital_cost":4871.7759904683,
        "active":true,
        "build_year":0,
        "lifetime":null,
        "length":115.6980733949,
        "carrier":"AC",
        "terrain_factor":1.0,
        "num_parallel":4.5789473684,
        "v_ang_min":null,
        "v_ang_max":null,
        "sub_network":"",
        "x_pu":0.0,
        "r_pu":0.0,
        "g_pu":0.0,
        "b_pu":0.0,
        "x_pu_eff":0.0000430456,
        "r_pu_eff":0.0000052495,
        "s_nom_opt":7775.5226170939,
        "dc":0.0,
        "i_nom":2.58,
        "v_nom":380.0,
        "id":"33",
        "location0":"DE0 15",
        "location1":"DE0 26",
        "location":null
    },
    "34":{
        "bus0":"DE0 15",
        "bus1":"DE0 27",
        "type":"Al\/St 240\/40 4-bundle 380.0",
        "x":3.7442800048,
        "r":0.4566195128,
        "g":0.0,
        "b":0.0021717407,
        "s_nom":9741.7465620904,
        "s_nom_mod":0.0,
        "s_nom_extendable":true,
        "s_nom_min":9741.7465620904,
        "s_nom_max":29741.7465620904,
        "s_max_pu":0.7,
        "capital_cost":3676.0100892855,
        "active":true,
        "build_year":0,
        "lifetime":null,
        "length":87.3184682332,
        "carrier":"AC",
        "terrain_factor":1.0,
        "num_parallel":5.7368421053,
        "v_ang_min":null,
        "v_ang_max":null,
        "sub_network":"",
        "x_pu":0.0,
        "r_pu":0.0,
        "g_pu":0.0,
        "b_pu":0.0,
        "x_pu_eff":0.0000259299,
        "r_pu_eff":0.0000031622,
        "s_nom_opt":9741.7466955265,
        "dc":0.0,
        "i_nom":2.58,
        "v_nom":380.0,
        "id":"34",
        "location0":"DE0 15",
        "location1":"DE0 27",
        "location":null
    },
    "35":{
        "bus0":"DE0 15",
        "bus1":"DE0 4",
        "type":"Al\/St 240\/40 4-bundle 380.0",
        "x":3.7921280831,
        "r":0.4624546443,
        "g":0.0,
        "b":0.0010001021,
        "s_nom":6568.9758927857,
        "s_nom_mod":0.0,
        "s_nom_extendable":true,
        "s_nom_min":6568.9758927857,
        "s_nom_max":26568.9758927857,
        "s_max_pu":0.7,
        "capital_cost":2511.2161559025,
        "active":true,
        "build_year":0,
        "lifetime":null,
        "length":59.6323093948,
        "carrier":"AC",
        "terrain_factor":1.0,
        "num_parallel":3.8684210526,
        "v_ang_min":null,
        "v_ang_max":null,
        "sub_network":"",
        "x_pu":0.0,
        "r_pu":0.0,
        "g_pu":0.0,
        "b_pu":0.0,
        "x_pu_eff":0.0000262613,
        "r_pu_eff":0.0000032026,
        "s_nom_opt":6568.9759586902,
        "dc":0.0,
        "i_nom":2.58,
        "v_nom":380.0,
        "id":"35",
        "location0":"DE0 15",
        "location1":"DE0 4",
        "location":null
    },
    "36":{
        "bus0":"DE0 16",
        "bus1":"DE0 18",
        "type":"Al\/St 240\/40 4-bundle 380.0",
        "x":7.4785284934,
        "r":0.9120156699,
        "g":0.0,
        "b":0.0016881873,
        "s_nom":6077.4198735977,
        "s_nom_mod":0.0,
        "s_nom_extendable":true,
        "s_nom_min":6077.4198735977,
        "s_nom_max":26077.4198735977,
        "s_max_pu":0.7,
        "capital_cost":4581.0277898805,
        "active":true,
        "build_year":0,
        "lifetime":null,
        "length":108.8018693949,
        "carrier":"AC",
        "terrain_factor":1.0,
        "num_parallel":3.5789473684,
        "v_ang_min":null,
        "v_ang_max":null,
        "sub_network":"",
        "x_pu":0.0,
        "r_pu":0.0,
        "g_pu":0.0,
        "b_pu":0.0,
        "x_pu_eff":0.0000517904,
        "r_pu_eff":0.0000063159,
        "s_nom_opt":6077.4199391422,
        "dc":0.0,
        "i_nom":2.58,
        "v_nom":380.0,
        "id":"36",
        "location0":"DE0 16",
        "location1":"DE0 18",
        "location":null
    },
    "37":{
        "bus0":"DE0 16",
        "bus1":"DE0 35",
        "type":"Al\/St 240\/40 4-bundle 380.0",
        "x":33.448498483,
        "r":4.0790851809,
        "g":0.0,
        "b":0.0001975826,
        "s_nom":983.1120383761,
        "s_nom_mod":0.0,
        "s_nom_extendable":true,
        "s_nom_min":983.1120383761,
        "s_nom_max":20983.1120383761,
        "s_max_pu":0.7,
        "capital_cost":3315.4417032602,
        "active":true,
        "build_year":0,
        "lifetime":null,
        "length":78.7191877006,
        "carrier":"AC",
        "terrain_factor":1.0,
        "num_parallel":0.5789473684,
        "v_ang_min":null,
        "v_ang_max":null,
        "sub_network":"",
        "x_pu":0.0,
        "r_pu":0.0,
        "g_pu":0.0,
        "b_pu":0.0,
        "x_pu_eff":0.0002316378,
        "r_pu_eff":0.0000282485,
        "s_nom_opt":983.1120840226,
        "dc":0.0,
        "i_nom":2.58,
        "v_nom":380.0,
        "id":"37",
        "location0":"DE0 16",
        "location1":"DE0 35",
        "location":null
    },
    "38":{
        "bus0":"DE0 17",
        "bus1":"DE0 36",
        "type":"Al\/St 240\/40 4-bundle 380.0",
        "x":26.2922562263,
        "r":3.2063727105,
        "g":0.0,
        "b":0.0018534535,
        "s_nom":3396.2052234811,
        "s_nom_mod":0.0,
        "s_nom_extendable":true,
        "s_nom_min":3396.2052234811,
        "s_nom_max":23396.2052234811,
        "s_max_pu":0.7,
        "capital_cost":8998.9480933247,
        "active":true,
        "build_year":0,
        "lifetime":null,
        "length":213.7581807014,
        "carrier":"AC",
        "terrain_factor":1.0,
        "num_parallel":2.0,
        "v_ang_min":null,
        "v_ang_max":null,
        "sub_network":"",
        "x_pu":0.0,
        "r_pu":0.0,
        "g_pu":0.0,
        "b_pu":0.0,
        "x_pu_eff":0.0001820793,
        "r_pu_eff":0.0000222048,
        "s_nom_opt":3396.2052603014,
        "dc":0.0,
        "i_nom":2.58,
        "v_nom":380.0,
        "id":"38",
        "location0":"DE0 17",
        "location1":"DE0 36",
        "location":null
    },
    "39":{
        "bus0":"DE0 17",
        "bus1":"DE0 5",
        "type":"Al\/St 240\/40 4-bundle 380.0",
        "x":5.2457642098,
        "r":0.6397273427,
        "g":0.0,
        "b":0.0033281671,
        "s_nom":10188.6156704432,
        "s_nom_mod":0.0,
        "s_nom_extendable":true,
        "s_nom_min":10188.6156704432,
        "s_nom_max":30188.6156704432,
        "s_max_pu":0.7,
        "capital_cost":5386.3052839487,
        "active":true,
        "build_year":0,
        "lifetime":null,
        "length":127.9454685306,
        "carrier":"AC",
        "terrain_factor":1.0,
        "num_parallel":6.0,
        "v_ang_min":null,
        "v_ang_max":null,
        "sub_network":"",
        "x_pu":0.0,
        "r_pu":0.0,
        "g_pu":0.0,
        "b_pu":0.0,
        "x_pu_eff":0.000036328,
        "r_pu_eff":0.0000044302,
        "s_nom_opt":10188.6165829411,
        "dc":0.0,
        "i_nom":2.58,
        "v_nom":380.0,
        "id":"39",
        "location0":"DE0 17",
        "location1":"DE0 5",
        "location":null
    },
    "4":{
        "bus0":"DE0 1",
        "bus1":"DE0 25",
        "type":"Al\/St 240\/40 4-bundle 380.0",
        "x":18.8740771697,
        "r":2.301716728,
        "g":0.0,
        "b":0.0013305144,
        "s_nom":3396.2052234811,
        "s_nom_mod":0.0,
        "s_nom_extendable":true,
        "s_nom_min":3396.2052234811,
        "s_nom_max":23396.2052234811,
        "s_max_pu":0.7,
        "capital_cost":6460.5367483246,
        "active":true,
        "build_year":0,
        "lifetime":null,
        "length":153.4477818676,
        "carrier":"AC",
        "terrain_factor":1.0,
        "num_parallel":2.0,
        "v_ang_min":null,
        "v_ang_max":null,
        "sub_network":"",
        "x_pu":0.0,
        "r_pu":0.0,
        "g_pu":0.0,
        "b_pu":0.0,
        "x_pu_eff":0.0001307069,
        "r_pu_eff":0.0000159399,
        "s_nom_opt":3396.2052846924,
        "dc":0.0,
        "i_nom":2.58,
        "v_nom":380.0,
        "id":"4",
        "location0":"DE0 1",
        "location1":"DE0 25",
        "location":null
    },
    "40":{
        "bus0":"DE0 18",
        "bus1":"DE0 34",
        "type":"Al\/St 240\/40 4-bundle 380.0",
        "x":3.1865338963,
        "r":0.3886016947,
        "g":0.0,
        "b":0.0019339931,
        "s_nom":9965.1811162668,
        "s_nom_mod":0.0,
        "s_nom_extendable":true,
        "s_nom_min":9965.1811162668,
        "s_nom_max":29965.1811162668,
        "s_max_pu":0.7,
        "capital_cost":3200.613827114,
        "active":true,
        "build_year":0,
        "lifetime":null,
        "length":76.0159455372,
        "carrier":"AC",
        "terrain_factor":1.0,
        "num_parallel":5.8684210526,
        "v_ang_min":null,
        "v_ang_max":null,
        "sub_network":"",
        "x_pu":0.0,
        "r_pu":0.0,
        "g_pu":0.0,
        "b_pu":0.0,
        "x_pu_eff":0.0000220674,
        "r_pu_eff":0.0000026911,
        "s_nom_opt":9965.1812506311,
        "dc":0.0,
        "i_nom":2.58,
        "v_nom":380.0,
        "id":"40",
        "location0":"DE0 18",
        "location1":"DE0 34",
        "location":null
    },
    "41":{
        "bus0":"DE0 19",
        "bus1":"DE0 28",
        "type":"Al\/St 240\/40 4-bundle 380.0",
        "x":19.0449503464,
        "r":2.3225549203,
        "g":0.0,
        "b":0.0013425637,
        "s_nom":3396.21,
        "s_nom_mod":0.0,
        "s_nom_extendable":true,
        "s_nom_min":3396.21,
        "s_nom_max":23396.21,
        "s_max_pu":0.7,
        "capital_cost":6520.7738920164,
        "active":true,
        "build_year":2024,
        "lifetime":null,
        "length":154.8372124532,
        "carrier":"AC",
        "terrain_factor":1.0,
        "num_parallel":2.0000028129,
        "v_ang_min":null,
        "v_ang_max":null,
        "sub_network":"",
        "x_pu":0.0,
        "r_pu":0.0,
        "g_pu":0.0,
        "b_pu":0.0,
        "x_pu_eff":0.0001318902,
        "r_pu_eff":0.0000160842,
        "s_nom_opt":3396.2100606668,
        "dc":null,
        "i_nom":2.58,
        "v_nom":380.0,
        "id":"41",
        "location0":"DE0 19",
        "location1":"DE0 28",
        "location":null
    },
    "42":{
        "bus0":"DE0 19",
        "bus1":"DE0 31",
        "type":"Al\/St 240\/40 4-bundle 380.0",
        "x":3.5117004448,
        "r":0.4282561518,
        "g":0.0,
        "b":0.0016464793,
        "s_nom":8758.6345237143,
        "s_nom_mod":0.0,
        "s_nom_extendable":true,
        "s_nom_min":8758.6345237143,
        "s_nom_max":28758.6345237143,
        "s_max_pu":0.7,
        "capital_cost":3100.8589768822,
        "active":true,
        "build_year":0,
        "lifetime":null,
        "length":73.6300050464,
        "carrier":"AC",
        "terrain_factor":1.0,
        "num_parallel":5.1578947368,
        "v_ang_min":null,
        "v_ang_max":null,
        "sub_network":"",
        "x_pu":0.0,
        "r_pu":0.0,
        "g_pu":0.0,
        "b_pu":0.0,
        "x_pu_eff":0.0000243193,
        "r_pu_eff":0.0000029658,
        "s_nom_opt":8758.6347121434,
        "dc":0.0,
        "i_nom":2.58,
        "v_nom":380.0,
        "id":"42",
        "location0":"DE0 19",
        "location1":"DE0 31",
        "location":null
    },
    "43":{
        "bus0":"DE0 2",
        "bus1":"DE0 26",
        "type":"Al\/St 240\/40 4-bundle 380.0",
        "x":3.0612161557,
        "r":0.3733190434,
        "g":0.0,
        "b":0.0025450814,
        "s_nom":11663.2837280073,
        "s_nom_mod":0.0,
        "s_nom_extendable":true,
        "s_nom_min":11663.2837280073,
        "s_nom_max":31663.2837280073,
        "s_max_pu":0.7,
        "capital_cost":3599.3253465142,
        "active":true,
        "build_year":0,
        "lifetime":null,
        "length":85.4704125629,
        "carrier":"AC",
        "terrain_factor":1.0,
        "num_parallel":6.8684210526,
        "v_ang_min":null,
        "v_ang_max":null,
        "sub_network":"",
        "x_pu":0.0,
        "r_pu":0.0,
        "g_pu":0.0,
        "b_pu":0.0,
        "x_pu_eff":0.0000211996,
        "r_pu_eff":0.0000025853,
        "s_nom_opt":11663.2839100549,
        "dc":0.0,
        "i_nom":2.58,
        "v_nom":380.0,
        "id":"43",
        "location0":"DE0 2",
        "location1":"DE0 26",
        "location":null
    },
    "44":{
        "bus0":"DE0 2",
        "bus1":"DE0 28",
        "type":"Al\/St 240\/40 4-bundle 380.0",
        "x":7.6145450763,
        "r":0.9286030581,
        "g":0.0,
        "b":0.0021471273,
        "s_nom":6792.4104469621,
        "s_nom_mod":0.0,
        "s_nom_extendable":true,
        "s_nom_min":6792.4104469621,
        "s_nom_max":26792.4104469621,
        "s_max_pu":0.7,
        "capital_cost":5214.2904330222,
        "active":true,
        "build_year":0,
        "lifetime":null,
        "length":123.8137410788,
        "carrier":"AC",
        "terrain_factor":1.0,
        "num_parallel":4.0,
        "v_ang_min":null,
        "v_ang_max":null,
        "sub_network":"",
        "x_pu":0.0,
        "r_pu":0.0,
        "g_pu":0.0,
        "b_pu":0.0,
        "x_pu_eff":0.0000527323,
        "r_pu_eff":0.0000064308,
        "s_nom_opt":6792.410624593,
        "dc":0.0,
        "i_nom":2.58,
        "v_nom":380.0,
        "id":"44",
        "location0":"DE0 2",
        "location1":"DE0 28",
        "location":null
    },
    "45":{
        "bus0":"DE0 2",
        "bus1":"DE0 30",
        "type":"Al\/St 240\/40 4-bundle 380.0",
        "x":14.3350401964,
        "r":1.7481756337,
        "g":0.0,
        "b":0.0022737111,
        "s_nom":5094.3078352216,
        "s_nom_mod":0.0,
        "s_nom_extendable":true,
        "s_nom_min":5094.3078352216,
        "s_nom_max":25094.3078352216,
        "s_max_pu":0.7,
        "capital_cost":7361.9243144175,
        "active":true,
        "build_year":0,
        "lifetime":null,
        "length":174.8175633711,
        "carrier":"AC",
        "terrain_factor":1.0,
        "num_parallel":3.0,
        "v_ang_min":null,
        "v_ang_max":null,
        "sub_network":"",
        "x_pu":0.0,
        "r_pu":0.0,
        "g_pu":0.0,
        "b_pu":0.0,
        "x_pu_eff":0.0000992731,
        "r_pu_eff":0.0000121065,
        "s_nom_opt":5094.3079454506,
        "dc":0.0,
        "i_nom":2.58,
        "v_nom":380.0,
        "id":"45",
        "location0":"DE0 2",
        "location1":"DE0 30",
        "location":null
    },
    "46":{
        "bus0":"DE0 2",
        "bus1":"DE0 31",
        "type":"Al\/St 240\/40 4-bundle 380.0",
        "x":14.4082783275,
        "r":1.7571071131,
        "g":0.0,
        "b":0.0010157011,
        "s_nom":3396.2052234811,
        "s_nom_mod":0.0,
        "s_nom_extendable":true,
        "s_nom_min":3396.2052234811,
        "s_nom_max":23396.2052234811,
        "s_max_pu":0.7,
        "capital_cost":4933.3633100509,
        "active":true,
        "build_year":0,
        "lifetime":null,
        "length":117.1404742076,
        "carrier":"AC",
        "terrain_factor":1.0,
        "num_parallel":2.0,
        "v_ang_min":null,
        "v_ang_max":null,
        "sub_network":"",
        "x_pu":0.0,
        "r_pu":0.0,
        "g_pu":0.0,
        "b_pu":0.0,
        "x_pu_eff":0.0000997803,
        "r_pu_eff":0.0000121683,
        "s_nom_opt":3396.2052626334,
        "dc":0.0,
        "i_nom":2.58,
        "v_nom":380.0,
        "id":"46",
        "location0":"DE0 2",
        "location1":"DE0 31",
        "location":null
    },
    "47":{
        "bus0":"DE0 20",
        "bus1":"DE0 30",
        "type":"Al\/St 240\/40 4-bundle 380.0",
        "x":13.5741109154,
        "r":1.6553793799,
        "g":0.0,
        "b":0.0023000913,
        "s_nom":5265.43,
        "s_nom_mod":0.0,
        "s_nom_extendable":true,
        "s_nom_min":5265.43,
        "s_nom_max":25265.43,
        "s_max_pu":0.7,
        "capital_cost":7204.4041141983,
        "active":true,
        "build_year":2037,
        "lifetime":null,
        "length":171.0984991564,
        "carrier":"AC",
        "terrain_factor":1.0,
        "num_parallel":3.1007725703,
        "v_ang_min":null,
        "v_ang_max":null,
        "sub_network":"",
        "x_pu":0.0,
        "r_pu":0.0,
        "g_pu":0.0,
        "b_pu":0.0,
        "x_pu_eff":0.0000940035,
        "r_pu_eff":0.0000114638,
        "s_nom_opt":5265.4300618593,
        "dc":null,
        "i_nom":2.58,
        "v_nom":380.0,
        "id":"47",
        "location0":"DE0 20",
        "location1":"DE0 30",
        "location":null
    },
    "48":{
        "bus0":"DE0 21",
        "bus1":"DE0 29",
        "type":"Al\/St 240\/40 4-bundle 380.0",
        "x":24.9363356406,
        "r":3.0410165415,
        "g":0.0,
        "b":0.0004394672,
        "s_nom":1698.1026117405,
        "s_nom_mod":0.0,
        "s_nom_extendable":true,
        "s_nom_min":1698.1026117405,
        "s_nom_max":21698.1026117405,
        "s_max_pu":0.7,
        "capital_cost":4267.8642287307,
        "active":true,
        "build_year":0,
        "lifetime":null,
        "length":101.3672180514,
        "carrier":"AC",
        "terrain_factor":1.0,
        "num_parallel":1.0,
        "v_ang_min":null,
        "v_ang_max":null,
        "sub_network":"",
        "x_pu":0.0,
        "r_pu":0.0,
        "g_pu":0.0,
        "b_pu":0.0,
        "x_pu_eff":0.0001726893,
        "r_pu_eff":0.0000210597,
        "s_nom_opt":1698.1027775947,
        "dc":0.0,
        "i_nom":2.58,
        "v_nom":380.0,
        "id":"48",
        "location0":"DE0 21",
        "location1":"DE0 29",
        "location":null
    },
    "49":{
        "bus0":"DE0 21",
        "bus1":"DE0 9",
        "type":"Al\/St 240\/40 4-bundle 380.0",
        "x":11.6978331419,
        "r":1.4265650173,
        "g":0.0,
        "b":0.0008246303,
        "s_nom":3396.2052234811,
        "s_nom_mod":0.0,
        "s_nom_extendable":true,
        "s_nom_min":3396.2052234811,
        "s_nom_max":23396.2052234811,
        "s_max_pu":0.7,
        "capital_cost":4004.8495016662,
        "active":true,
        "build_year":0,
        "lifetime":null,
        "length":95.1043344869,
        "carrier":"AC",
        "terrain_factor":1.0,
        "num_parallel":2.0,
        "v_ang_min":null,
        "v_ang_max":null,
        "sub_network":"",
        "x_pu":0.0,
        "r_pu":0.0,
        "g_pu":0.0,
        "b_pu":0.0,
        "x_pu_eff":0.0000810099,
        "r_pu_eff":0.0000098793,
        "s_nom_opt":3396.2053786824,
        "dc":0.0,
        "i_nom":2.58,
        "v_nom":380.0,
        "id":"49",
        "location0":"DE0 21",
        "location1":"DE0 9",
        "location":null
    },
    "5":{
        "bus0":"DE0 1",
        "bus1":"DE0 29",
        "type":"Al\/St 240\/40 4-bundle 380.0",
        "x":31.5679715273,
        "r":3.8497526253,
        "g":0.0,
        "b":0.0009250506,
        "s_nom":2189.6586309286,
        "s_nom_mod":0.0,
        "s_nom_extendable":true,
        "s_nom_min":2189.6586309286,
        "s_nom_max":22189.6586309286,
        "s_max_pu":0.7,
        "capital_cost":6967.1522458482,
        "active":true,
        "build_year":0,
        "lifetime":null,
        "length":165.4718233673,
        "carrier":"AC",
        "terrain_factor":1.0,
        "num_parallel":1.2894736842,
        "v_ang_min":null,
        "v_ang_max":null,
        "sub_network":"",
        "x_pu":0.0,
        "r_pu":0.0,
        "g_pu":0.0,
        "b_pu":0.0,
        "x_pu_eff":0.0002186148,
        "r_pu_eff":0.0000266603,
        "s_nom_opt":2189.6586791371,
        "dc":0.0,
        "i_nom":2.58,
        "v_nom":380.0,
        "id":"5",
        "location0":"DE0 1",
        "location1":"DE0 29",
        "location":null
    },
    "50":{
        "bus0":"DE0 22",
        "bus1":"DE0 3",
        "type":"Al\/St 240\/40 4-bundle 380.0",
        "x":34.7119823949,
        "r":4.2331685847,
        "g":0.0,
        "b":0.001017181,
        "s_nom":2189.6586309286,
        "s_nom_mod":0.0,
        "s_nom_extendable":true,
        "s_nom_min":2189.6586309286,
        "s_nom_max":22189.6586309286,
        "s_max_pu":0.7,
        "capital_cost":7659.9649717665,
        "active":true,
        "build_year":0,
        "lifetime":null,
        "length":181.9519830284,
        "carrier":"AC",
        "terrain_factor":1.0,
        "num_parallel":1.2894736842,
        "v_ang_min":null,
        "v_ang_max":null,
        "sub_network":"",
        "x_pu":0.0,
        "r_pu":0.0,
        "g_pu":0.0,
        "b_pu":0.0,
        "x_pu_eff":0.0002403877,
        "r_pu_eff":0.0000293156,
        "s_nom_opt":2189.6586357162,
        "dc":0.0,
        "i_nom":2.58,
        "v_nom":380.0,
        "id":"50",
        "location0":"DE0 22",
        "location1":"DE0 3",
        "location":null
    },
    "51":{
        "bus0":"DE0 23",
        "bus1":"DE0 33",
        "type":"Al\/St 240\/40 4-bundle 380.0",
        "x":16.3381410295,
        "r":1.9924562231,
        "g":0.0,
        "b":0.0011517454,
        "s_nom":3396.2052234811,
        "s_nom_mod":0.0,
        "s_nom_extendable":true,
        "s_nom_min":3396.2052234811,
        "s_nom_max":23396.2052234811,
        "s_max_pu":0.7,
        "capital_cost":5594.0985146288,
        "active":true,
        "build_year":0,
        "lifetime":null,
        "length":132.8304148737,
        "carrier":"AC",
        "terrain_factor":1.0,
        "num_parallel":2.0,
        "v_ang_min":null,
        "v_ang_max":null,
        "sub_network":"",
        "x_pu":0.0,
        "r_pu":0.0,
        "g_pu":0.0,
        "b_pu":0.0,
        "x_pu_eff":0.000113145,
        "r_pu_eff":0.0000137982,
        "s_nom_opt":3396.2052584001,
        "dc":0.0,
        "i_nom":2.58,
        "v_nom":380.0,
        "id":"51",
        "location0":"DE0 23",
        "location1":"DE0 33",
        "location":null
    },
    "52":{
        "bus0":"DE0 23",
        "bus1":"DE0 36",
        "type":"Al\/St 240\/40 4-bundle 380.0",
        "x":2.6095683096,
        "r":0.3182400378,
        "g":0.0,
        "b":0.0009642593,
        "s_nom":7775.5224853382,
        "s_nom_mod":0.0,
        "s_nom_extendable":true,
        "s_nom_min":7775.5224853382,
        "s_nom_max":27775.5224853382,
        "s_max_pu":0.7,
        "capital_cost":2045.6310711177,
        "active":true,
        "build_year":0,
        "lifetime":null,
        "length":48.5734794472,
        "carrier":"AC",
        "terrain_factor":1.0,
        "num_parallel":4.5789473684,
        "v_ang_min":null,
        "v_ang_max":null,
        "sub_network":"",
        "x_pu":0.0,
        "r_pu":0.0,
        "g_pu":0.0,
        "b_pu":0.0,
        "x_pu_eff":0.0000180718,
        "r_pu_eff":0.0000022039,
        "s_nom_opt":7775.5226585694,
        "dc":0.0,
        "i_nom":2.58,
        "v_nom":380.0,
        "id":"52",
        "location0":"DE0 23",
        "location1":"DE0 36",
        "location":null
    },
    "53":{
        "bus0":"DE0 23",
        "bus1":"DE0 38",
        "type":"Al\/St 240\/40 4-bundle 380.0",
        "x":17.0375924967,
        "r":2.0777551825,
        "g":0.0,
        "b":0.0012010527,
        "s_nom":3396.2052234811,
        "s_nom_mod":0.0,
        "s_nom_extendable":true,
        "s_nom_min":3396.2052234811,
        "s_nom_max":23396.2052234811,
        "s_max_pu":0.7,
        "capital_cost":5832.591228344,
        "active":true,
        "build_year":0,
        "lifetime":null,
        "length":138.5170121682,
        "carrier":"AC",
        "terrain_factor":1.0,
        "num_parallel":2.0,
        "v_ang_min":null,
        "v_ang_max":null,
        "sub_network":"",
        "x_pu":0.0,
        "r_pu":0.0,
        "g_pu":0.0,
        "b_pu":0.0,
        "x_pu_eff":0.0001179889,
        "r_pu_eff":0.0000143889,
        "s_nom_opt":3396.2052565467,
        "dc":0.0,
        "i_nom":2.58,
        "v_nom":380.0,
        "id":"53",
        "location0":"DE0 23",
        "location1":"DE0 38",
        "location":null
    },
    "54":{
        "bus0":"DE0 24",
        "bus1":"DE0 27",
        "type":"Al\/St 240\/40 4-bundle 380.0",
        "x":3.6173068008,
        "r":0.4411349757,
        "g":0.0,
        "b":0.0021954408,
        "s_nom":9965.1811162668,
        "s_nom_mod":0.0,
        "s_nom_extendable":true,
        "s_nom_min":9965.1811162668,
        "s_nom_max":29965.1811162668,
        "s_max_pu":0.7,
        "capital_cost":3633.4875780112,
        "active":true,
        "build_year":0,
        "lifetime":null,
        "length":86.2921926165,
        "carrier":"AC",
        "terrain_factor":1.0,
        "num_parallel":5.8684210526,
        "v_ang_min":null,
        "v_ang_max":null,
        "sub_network":"",
        "x_pu":0.0,
        "r_pu":0.0,
        "g_pu":0.0,
        "b_pu":0.0,
        "x_pu_eff":0.0000250506,
        "r_pu_eff":0.000003055,
        "s_nom_opt":9965.1812210137,
        "dc":0.0,
        "i_nom":2.58,
        "v_nom":380.0,
        "id":"54",
        "location0":"DE0 24",
        "location1":"DE0 27",
        "location":null
    },
    "55":{
        "bus0":"DE0 24",
        "bus1":"DE0 34",
        "type":"Al\/St 240\/40 4-bundle 380.0",
        "x":17.011193718,
        "r":2.0745358193,
        "g":0.0,
        "b":0.0015714478,
        "s_nom":3887.7612426691,
        "s_nom_mod":0.0,
        "s_nom_extendable":true,
        "s_nom_min":3887.7612426691,
        "s_nom_max":23887.7612426691,
        "s_max_pu":0.7,
        "capital_cost":6665.2416287313,
        "active":true,
        "build_year":0,
        "lifetime":null,
        "length":158.3198388391,
        "carrier":"AC",
        "terrain_factor":1.0,
        "num_parallel":2.2894736842,
        "v_ang_min":null,
        "v_ang_max":null,
        "sub_network":"",
        "x_pu":0.0,
        "r_pu":0.0,
        "g_pu":0.0,
        "b_pu":0.0,
        "x_pu_eff":0.0001178061,
        "r_pu_eff":0.0000143666,
        "s_nom_opt":3887.761280907,
        "dc":0.0,
        "i_nom":2.58,
        "v_nom":380.0,
        "id":"55",
        "location0":"DE0 24",
        "location1":"DE0 34",
        "location":null
    },
    "56":{
        "bus0":"DE0 24",
        "bus1":"DE0 8",
        "type":"Al\/St 240\/40 4-bundle 380.0",
        "x":127.2339930292,
        "r":15.5163406133,
        "g":0.0,
        "b":0.000187895,
        "s_nom":491.556019188,
        "s_nom_mod":0.0,
        "s_nom_extendable":true,
        "s_nom_min":491.556019188,
        "s_nom_max":20491.556019188,
        "s_max_pu":0.7,
        "capital_cost":6303.1718496891,
        "active":true,
        "build_year":0,
        "lifetime":null,
        "length":149.7190760934,
        "carrier":"AC",
        "terrain_factor":1.0,
        "num_parallel":0.2894736842,
        "v_ang_min":null,
        "v_ang_max":null,
        "sub_network":"",
        "x_pu":0.0,
        "r_pu":0.0,
        "g_pu":0.0,
        "b_pu":0.0,
        "x_pu_eff":0.0008811218,
        "r_pu_eff":0.0001074539,
        "s_nom_opt":491.556034448,
        "dc":0.0,
        "i_nom":2.58,
        "v_nom":380.0,
        "id":"56",
        "location0":"DE0 24",
        "location1":"DE0 8",
        "location":null
    },
    "57":{
        "bus0":"DE0 25",
        "bus1":"DE0 28",
        "type":"Al\/St 240\/40 4-bundle 380.0",
        "x":21.8839377938,
        "r":2.6687729017,
        "g":0.0,
        "b":0.0015426923,
        "s_nom":3396.2052234811,
        "s_nom_mod":0.0,
        "s_nom_extendable":true,
        "s_nom_min":3396.2052234811,
        "s_nom_max":23396.2052234811,
        "s_max_pu":0.7,
        "capital_cost":7492.7451800805,
        "active":true,
        "build_year":0,
        "lifetime":null,
        "length":177.9181934459,
        "carrier":"AC",
        "terrain_factor":1.0,
        "num_parallel":2.0,
        "v_ang_min":null,
        "v_ang_max":null,
        "sub_network":"",
        "x_pu":0.0,
        "r_pu":0.0,
        "g_pu":0.0,
        "b_pu":0.0,
        "x_pu_eff":0.0001515508,
        "r_pu_eff":0.0000184818,
        "s_nom_opt":3396.2052539548,
        "dc":0.0,
        "i_nom":2.58,
        "v_nom":380.0,
        "id":"57",
        "location0":"DE0 25",
        "location1":"DE0 28",
        "location":null
    },
    "58":{
        "bus0":"DE0 25",
        "bus1":"DE0 33",
        "type":"Al\/St 240\/40 4-bundle 380.0",
        "x":11.5888896621,
        "r":1.4132792271,
        "g":0.0,
        "b":0.0019637017,
        "s_nom":5265.43,
        "s_nom_mod":0.0,
        "s_nom_extendable":true,
        "s_nom_min":5265.43,
        "s_nom_max":25265.43,
        "s_max_pu":0.7,
        "capital_cost":6151.8939315473,
        "active":true,
        "build_year":2037,
        "lifetime":null,
        "length":146.075248716,
        "carrier":"AC",
        "terrain_factor":1.0,
        "num_parallel":3.1007725703,
        "v_ang_min":null,
        "v_ang_max":null,
        "sub_network":"",
        "x_pu":0.0,
        "r_pu":0.0,
        "g_pu":0.0,
        "b_pu":0.0,
        "x_pu_eff":0.0000802555,
        "r_pu_eff":0.0000097873,
        "s_nom_opt":5265.4301247563,
        "dc":null,
        "i_nom":2.58,
        "v_nom":380.0,
        "id":"58",
        "location0":"DE0 25",
        "location1":"DE0 33",
        "location":null
    },
    "59":{
        "bus0":"DE0 26",
        "bus1":"DE0 4",
        "type":"Al\/St 240\/40 4-bundle 380.0",
        "x":11.7825137184,
        "r":1.4368919169,
        "g":0.0,
        "b":0.0010884366,
        "s_nom":3887.7612426691,
        "s_nom_mod":0.0,
        "s_nom_extendable":true,
        "s_nom_min":3887.7612426691,
        "s_nom_max":23887.7612426691,
        "s_max_pu":0.7,
        "capital_cost":4616.3179069403,
        "active":true,
        "build_year":0,
        "lifetime":null,
        "length":109.6575410252,
        "carrier":"AC",
        "terrain_factor":1.0,
        "num_parallel":2.2894736842,
        "v_ang_min":null,
        "v_ang_max":null,
        "sub_network":"",
        "x_pu":0.0,
        "r_pu":0.0,
        "g_pu":0.0,
        "b_pu":0.0,
        "x_pu_eff":0.0000815964,
        "r_pu_eff":0.0000099508,
        "s_nom_opt":3924.5463758412,
        "dc":0.0,
        "i_nom":2.58,
        "v_nom":380.0,
        "id":"59",
        "location0":"DE0 26",
        "location1":"DE0 4",
        "location":null
    },
    "6":{
        "bus0":"DE0 1",
        "bus1":"DE0 34",
        "type":"Al\/St 240\/40 4-bundle 380.0",
        "x":7.5217364723,
        "r":0.9172849356,
        "g":0.0,
        "b":0.001697941,
        "s_nom":6077.4198735977,
        "s_nom_mod":0.0,
        "s_nom_extendable":true,
        "s_nom_min":6077.4198735977,
        "s_nom_max":26077.4198735977,
        "s_max_pu":0.7,
        "capital_cost":4608.4625546845,
        "active":true,
        "build_year":0,
        "lifetime":null,
        "length":109.4304835501,
        "carrier":"AC",
        "terrain_factor":1.0,
        "num_parallel":3.5789473684,
        "v_ang_min":null,
        "v_ang_max":null,
        "sub_network":"",
        "x_pu":0.0,
        "r_pu":0.0,
        "g_pu":0.0,
        "b_pu":0.0,
        "x_pu_eff":0.0000520896,
        "r_pu_eff":0.0000063524,
        "s_nom_opt":6077.4199284711,
        "dc":0.0,
        "i_nom":2.58,
        "v_nom":380.0,
        "id":"6",
        "location0":"DE0 1",
        "location1":"DE0 34",
        "location":null
    },
    "60":{
        "bus0":"DE0 26",
        "bus1":"DE0 7",
        "type":"Al\/St 240\/40 4-bundle 380.0",
        "x":18.6258981295,
        "r":2.2714509914,
        "g":0.0,
        "b":0.0013130192,
        "s_nom":3396.2052234811,
        "s_nom_mod":0.0,
        "s_nom_extendable":true,
        "s_nom_min":3396.2052234811,
        "s_nom_max":23396.2052234811,
        "s_max_pu":0.7,
        "capital_cost":6376.4464608537,
        "active":true,
        "build_year":0,
        "lifetime":null,
        "length":151.4300660933,
        "carrier":"AC",
        "terrain_factor":1.0,
        "num_parallel":2.0,
        "v_ang_min":null,
        "v_ang_max":null,
        "sub_network":"",
        "x_pu":0.0,
        "r_pu":0.0,
        "g_pu":0.0,
        "b_pu":0.0,
        "x_pu_eff":0.0001289882,
        "r_pu_eff":0.0000157303,
        "s_nom_opt":4933.490995646,
        "dc":0.0,
        "i_nom":2.58,
        "v_nom":380.0,
        "id":"60",
        "location0":"DE0 26",
        "location1":"DE0 7",
        "location":null
    },
    "61":{
        "bus0":"DE0 27",
        "bus1":"DE0 4",
        "type":"Al\/St 240\/40 4-bundle 380.0",
        "x":5.8992677272,
        "r":0.7194228936,
        "g":0.0,
        "b":0.0021798332,
        "s_nom":7775.5224853382,
        "s_nom_mod":0.0,
        "s_nom_extendable":true,
        "s_nom_min":7775.5224853382,
        "s_nom_max":27775.5224853382,
        "s_max_pu":0.7,
        "capital_cost":4623.5431307856,
        "active":true,
        "build_year":0,
        "lifetime":null,
        "length":109.8066521755,
        "carrier":"AC",
        "terrain_factor":1.0,
        "num_parallel":4.5789473684,
        "v_ang_min":null,
        "v_ang_max":null,
        "sub_network":"",
        "x_pu":0.0,
        "r_pu":0.0,
        "g_pu":0.0,
        "b_pu":0.0,
        "x_pu_eff":0.0000408537,
        "r_pu_eff":0.0000049822,
        "s_nom_opt":7775.5225814814,
        "dc":0.0,
        "i_nom":2.58,
        "v_nom":380.0,
        "id":"61",
        "location0":"DE0 27",
        "location1":"DE0 4",
        "location":null
    },
    "62":{
        "bus0":"DE0 27",
        "bus1":"DE0 8",
        "type":"Al\/St 240\/40 4-bundle 380.0",
        "x":19.0885456515,
        "r":2.3278714209,
        "g":0.0,
        "b":0.0013456332,
        "s_nom":3396.2052234811,
        "s_nom_mod":0.0,
        "s_nom_extendable":true,
        "s_nom_min":3396.2052234811,
        "s_nom_max":23396.2052234811,
        "s_max_pu":0.7,
        "capital_cost":6534.6429054494,
        "active":true,
        "build_year":0,
        "lifetime":null,
        "length":155.1914280611,
        "carrier":"AC",
        "terrain_factor":1.0,
        "num_parallel":2.0,
        "v_ang_min":null,
        "v_ang_max":null,
        "sub_network":"",
        "x_pu":0.0,
        "r_pu":0.0,
        "g_pu":0.0,
        "b_pu":0.0,
        "x_pu_eff":0.0001321921,
        "r_pu_eff":0.000016121,
        "s_nom_opt":3396.2052518633,
        "dc":0.0,
        "i_nom":2.58,
        "v_nom":380.0,
        "id":"62",
        "location0":"DE0 27",
        "location1":"DE0 8",
        "location":null
    },
    "63":{
        "bus0":"DE0 28",
        "bus1":"DE0 31",
        "type":"Al\/St 240\/40 4-bundle 380.0",
        "x":8.0882512019,
        "r":0.9863720978,
        "g":0.0,
        "b":0.0029886825,
        "s_nom":7775.5224853382,
        "s_nom_mod":0.0,
        "s_nom_extendable":true,
        "s_nom_min":7775.5224853382,
        "s_nom_max":27775.5224853382,
        "s_max_pu":0.7,
        "capital_cost":6339.9861151823,
        "active":true,
        "build_year":0,
        "lifetime":null,
        "length":150.5515307164,
        "carrier":"AC",
        "terrain_factor":1.0,
        "num_parallel":4.5789473684,
        "v_ang_min":null,
        "v_ang_max":null,
        "sub_network":"",
        "x_pu":0.0,
        "r_pu":0.0,
        "g_pu":0.0,
        "b_pu":0.0,
        "x_pu_eff":0.0000560128,
        "r_pu_eff":0.0000068308,
        "s_nom_opt":7775.5226133988,
        "dc":0.0,
        "i_nom":2.58,
        "v_nom":380.0,
        "id":"63",
        "location0":"DE0 28",
        "location1":"DE0 31",
        "location":null
    },
    "64":{
        "bus0":"DE0 28",
        "bus1":"DE0 6",
        "type":"Al\/St 240\/40 4-bundle 380.0",
        "x":8.5936122473,
        "r":1.0480014936,
        "g":0.0,
        "b":0.0006058005,
        "s_nom":3396.2052234811,
        "s_nom_mod":0.0,
        "s_nom_extendable":true,
        "s_nom_min":3396.2052234811,
        "s_nom_max":23396.2052234811,
        "s_max_pu":0.7,
        "capital_cost":2941.2176923397,
        "active":true,
        "build_year":0,
        "lifetime":null,
        "length":69.8667662379,
        "carrier":"AC",
        "terrain_factor":1.0,
        "num_parallel":2.0,
        "v_ang_min":null,
        "v_ang_max":null,
        "sub_network":"",
        "x_pu":0.0,
        "r_pu":0.0,
        "g_pu":0.0,
        "b_pu":0.0,
        "x_pu_eff":0.0000595126,
        "r_pu_eff":0.0000072576,
        "s_nom_opt":3396.2052696921,
        "dc":0.0,
        "i_nom":2.58,
        "v_nom":380.0,
        "id":"64",
        "location0":"DE0 28",
        "location1":"DE0 6",
        "location":null
    },
    "65":{
        "bus0":"DE0 29",
        "bus1":"DE0 35",
        "type":"Al\/St 240\/40 4-bundle 380.0",
        "x":25.0880456186,
        "r":3.0595177584,
        "g":0.0,
        "b":0.0007351664,
        "s_nom":2189.6586309286,
        "s_nom_mod":0.0,
        "s_nom_extendable":true,
        "s_nom_min":2189.6586309286,
        "s_nom_max":22189.6586309286,
        "s_max_pu":0.7,
        "capital_cost":5536.2179113274,
        "active":true,
        "build_year":0,
        "lifetime":null,
        "length":131.5055878596,
        "carrier":"AC",
        "terrain_factor":1.0,
        "num_parallel":1.2894736842,
        "v_ang_min":null,
        "v_ang_max":null,
        "sub_network":"",
        "x_pu":0.0,
        "r_pu":0.0,
        "g_pu":0.0,
        "b_pu":0.0,
        "x_pu_eff":0.0001737399,
        "r_pu_eff":0.0000211878,
        "s_nom_opt":2189.6587013945,
        "dc":0.0,
        "i_nom":2.58,
        "v_nom":380.0,
        "id":"65",
        "location0":"DE0 29",
        "location1":"DE0 35",
        "location":null
    },
    "66":{
        "bus0":"DE0 29",
        "bus1":"DE0 9",
        "type":"Al\/St 240\/40 4-bundle 380.0",
        "x":8.9150301329,
        "r":1.0871987967,
        "g":0.0,
        "b":0.0010449647,
        "s_nom":4379.3172618571,
        "s_nom_mod":0.0,
        "s_nom_extendable":true,
        "s_nom_min":4379.3172618571,
        "s_nom_max":24379.3172618571,
        "s_max_pu":0.7,
        "capital_cost":3936.042487814,
        "active":true,
        "build_year":0,
        "lifetime":null,
        "length":93.4609491897,
        "carrier":"AC",
        "terrain_factor":1.0,
        "num_parallel":2.5789473684,
        "v_ang_min":null,
        "v_ang_max":null,
        "sub_network":"",
        "x_pu":0.0,
        "r_pu":0.0,
        "g_pu":0.0,
        "b_pu":0.0,
        "x_pu_eff":0.0000617384,
        "r_pu_eff":0.0000075291,
        "s_nom_opt":4379.3173013891,
        "dc":0.0,
        "i_nom":2.58,
        "v_nom":380.0,
        "id":"66",
        "location0":"DE0 29",
        "location1":"DE0 9",
        "location":null
    },
    "67":{
        "bus0":"DE0 29",
        "bus1":"DE0 9",
        "type":"Al\/St 240\/40 4-bundle 380.0",
        "x":11.4956805825,
        "r":1.4019122662,
        "g":0.0,
        "b":0.0008103819,
        "s_nom":3396.21,
        "s_nom_mod":0.0,
        "s_nom_extendable":true,
        "s_nom_min":3396.21,
        "s_nom_max":23396.21,
        "s_max_pu":0.7,
        "capital_cost":3936.3346764478,
        "active":true,
        "build_year":2025,
        "lifetime":null,
        "length":93.4609491897,
        "carrier":"AC",
        "terrain_factor":1.0,
        "num_parallel":2.0000028129,
        "v_ang_min":null,
        "v_ang_max":null,
        "sub_network":"",
        "x_pu":0.0,
        "r_pu":0.0,
        "g_pu":0.0,
        "b_pu":0.0,
        "x_pu_eff":0.00007961,
        "r_pu_eff":0.0000097085,
        "s_nom_opt":3396.2100829261,
        "dc":null,
        "i_nom":2.58,
        "v_nom":380.0,
        "id":"67",
        "location0":"DE0 29",
        "location1":"DE0 9",
        "location":null
    },
    "68":{
        "bus0":"DE0 3",
        "bus1":"DE0 38",
        "type":"Al\/St 240\/40 4-bundle 380.0",
        "x":12.3365868189,
        "r":1.5044618072,
        "g":0.0,
        "b":0.0008696587,
        "s_nom":3396.2052234811,
        "s_nom_mod":0.0,
        "s_nom_extendable":true,
        "s_nom_min":3396.2052234811,
        "s_nom_max":23396.2052234811,
        "s_max_pu":0.7,
        "capital_cost":4222.7540282138,
        "active":true,
        "build_year":0,
        "lifetime":null,
        "length":100.2974538124,
        "carrier":"AC",
        "terrain_factor":1.0,
        "num_parallel":2.0,
        "v_ang_min":null,
        "v_ang_max":null,
        "sub_network":"",
        "x_pu":0.0,
        "r_pu":0.0,
        "g_pu":0.0,
        "b_pu":0.0,
        "x_pu_eff":0.0000854334,
        "r_pu_eff":0.0000104187,
        "s_nom_opt":3396.2052596718,
        "dc":0.0,
        "i_nom":2.58,
        "v_nom":380.0,
        "id":"68",
        "location0":"DE0 3",
        "location1":"DE0 38",
        "location":null
    },
    "69":{
        "bus0":"DE0 30",
        "bus1":"DE0 31",
        "type":"Al\/St 240\/40 4-bundle 380.0",
        "x":8.2801395884,
        "r":1.0097731205,
        "g":0.0,
        "b":0.0018691413,
        "s_nom":6077.4198735977,
        "s_nom_mod":0.0,
        "s_nom_extendable":true,
        "s_nom_min":6077.4198735977,
        "s_nom_max":26077.4198735977,
        "s_max_pu":0.7,
        "capital_cost":5072.2008741174,
        "active":true,
        "build_year":0,
        "lifetime":null,
        "length":120.4641617478,
        "carrier":"AC",
        "terrain_factor":1.0,
        "num_parallel":3.5789473684,
        "v_ang_min":null,
        "v_ang_max":null,
        "sub_network":"",
        "x_pu":0.0,
        "r_pu":0.0,
        "g_pu":0.0,
        "b_pu":0.0,
        "x_pu_eff":0.0000573417,
        "r_pu_eff":0.0000069929,
        "s_nom_opt":6077.4199764577,
        "dc":0.0,
        "i_nom":2.58,
        "v_nom":380.0,
        "id":"69",
        "location0":"DE0 30",
        "location1":"DE0 31",
        "location":null
    },
    "7":{
        "bus0":"DE0 1",
        "bus1":"DE0 35",
        "type":"Al\/St 240\/40 4-bundle 380.0",
        "x":18.1989762181,
        "r":2.2193873437,
        "g":0.0,
        "b":0.0012829236,
        "s_nom":3396.2052234811,
        "s_nom_mod":0.0,
        "s_nom_extendable":true,
        "s_nom_min":3396.2052234811,
        "s_nom_max":23396.2052234811,
        "s_max_pu":0.7,
        "capital_cost":6230.7838769485,
        "active":true,
        "build_year":0,
        "lifetime":null,
        "length":147.9591562446,
        "carrier":"AC",
        "terrain_factor":1.0,
        "num_parallel":2.0,
        "v_ang_min":null,
        "v_ang_max":null,
        "sub_network":"",
        "x_pu":0.0,
        "r_pu":0.0,
        "g_pu":0.0,
        "b_pu":0.0,
        "x_pu_eff":0.0001260317,
        "r_pu_eff":0.0000153697,
        "s_nom_opt":3396.2052805087,
        "dc":0.0,
        "i_nom":2.58,
        "v_nom":380.0,
        "id":"7",
        "location0":"DE0 1",
        "location1":"DE0 35",
        "location":null
    },
    "70":{
        "bus0":"DE0 30",
        "bus1":"DE0 7",
        "type":"Al\/St 240\/40 4-bundle 380.0",
        "x":13.2467482628,
        "r":1.6154571052,
        "g":0.0,
        "b":0.0008149907,
        "s_nom":3172.7706693047,
        "s_nom_mod":0.0,
        "s_nom_extendable":true,
        "s_nom_min":3172.7706693047,
        "s_nom_max":23172.7706693047,
        "s_max_pu":0.7,
        "capital_cost":4236.8403947384,
        "active":true,
        "build_year":0,
        "lifetime":null,
        "length":100.6118021675,
        "carrier":"AC",
        "terrain_factor":1.0,
        "num_parallel":1.8684210526,
        "v_ang_min":null,
        "v_ang_max":null,
        "sub_network":"",
        "x_pu":0.0,
        "r_pu":0.0,
        "g_pu":0.0,
        "b_pu":0.0,
        "x_pu_eff":0.0000917365,
        "r_pu_eff":0.0000111874,
        "s_nom_opt":4518.9408511757,
        "dc":0.0,
        "i_nom":2.58,
        "v_nom":380.0,
        "id":"70",
        "location0":"DE0 30",
        "location1":"DE0 7",
        "location":null
    },
    "71":{
        "bus0":"DE0 33",
        "bus1":"DE0 38",
        "type":"Al\/St 240\/40 4-bundle 380.0",
        "x":2.4026569667,
        "r":0.2930069472,
        "g":0.0,
        "b":0.001524362,
        "s_nom":10188.6156704432,
        "s_nom_mod":0.0,
        "s_nom_extendable":true,
        "s_nom_min":10188.6156704432,
        "s_nom_max":30188.6156704432,
        "s_max_pu":0.7,
        "capital_cost":2467.8890062811,
        "active":true,
        "build_year":0,
        "lifetime":null,
        "length":58.6013894317,
        "carrier":"AC",
        "terrain_factor":1.0,
        "num_parallel":6.0,
        "v_ang_min":null,
        "v_ang_max":null,
        "sub_network":"",
        "x_pu":0.0,
        "r_pu":0.0,
        "g_pu":0.0,
        "b_pu":0.0,
        "x_pu_eff":0.0000166389,
        "r_pu_eff":0.0000020291,
        "s_nom_opt":10188.6159664842,
        "dc":0.0,
        "i_nom":2.58,
        "v_nom":380.0,
        "id":"71",
        "location0":"DE0 33",
        "location1":"DE0 38",
        "location":null
    },
    "72":{
        "bus0":"DE0 33",
        "bus1":"DE0 6",
        "type":"Al\/St 240\/40 4-bundle 380.0",
        "x":8.8832479871,
        "r":1.0833229253,
        "g":0.0,
        "b":0.0010412394,
        "s_nom":4379.3172618571,
        "s_nom_mod":0.0,
        "s_nom_extendable":true,
        "s_nom_min":4379.3172618571,
        "s_nom_max":24379.3172618571,
        "s_max_pu":0.7,
        "capital_cost":3922.1460372399,
        "active":true,
        "build_year":0,
        "lifetime":null,
        "length":93.1277602415,
        "carrier":"AC",
        "terrain_factor":1.0,
        "num_parallel":2.5789473684,
        "v_ang_min":null,
        "v_ang_max":null,
        "sub_network":"",
        "x_pu":0.0,
        "r_pu":0.0,
        "g_pu":0.0,
        "b_pu":0.0,
        "x_pu_eff":0.0000615183,
        "r_pu_eff":0.0000075022,
        "s_nom_opt":4379.317288273,
        "dc":0.0,
        "i_nom":2.58,
        "v_nom":380.0,
        "id":"72",
        "location0":"DE0 33",
        "location1":"DE0 6",
        "location":null
    },
    "73":{
        "bus0":"DE0 34",
        "bus1":"DE0 8",
        "type":"Al\/St 240\/40 4-bundle 380.0",
        "x":12.737774805,
        "r":1.5533871713,
        "g":0.0,
        "b":0.0014930432,
        "s_nom":4379.3172618571,
        "s_nom_mod":0.0,
        "s_nom_extendable":true,
        "s_nom_min":4379.3172618571,
        "s_nom_max":24379.3172618571,
        "s_max_pu":0.7,
        "capital_cost":5622.2668440043,
        "active":true,
        "build_year":0,
        "lifetime":null,
        "length":133.536791922,
        "carrier":"AC",
        "terrain_factor":1.0,
        "num_parallel":2.5789473684,
        "v_ang_min":null,
        "v_ang_max":null,
        "sub_network":"",
        "x_pu":0.0,
        "r_pu":0.0,
        "g_pu":0.0,
        "b_pu":0.0,
        "x_pu_eff":0.0000882117,
        "r_pu_eff":0.0000107575,
        "s_nom_opt":4379.3172774607,
        "dc":0.0,
        "i_nom":2.58,
        "v_nom":380.0,
        "id":"73",
        "location0":"DE0 34",
        "location1":"DE0 8",
        "location":null
    },
    "74":{
        "bus0":"DE0 36",
        "bus1":"DE0 37",
        "type":"Al\/St 240\/40 4-bundle 380.0",
        "x":3.1391525631,
        "r":0.3828234833,
        "g":0.0,
        "b":0.0019916305,
        "s_nom":10188.6156704432,
        "s_nom_mod":0.0,
        "s_nom_extendable":true,
        "s_nom_min":10188.6156704432,
        "s_nom_max":30188.6156704432,
        "s_max_pu":0.7,
        "capital_cost":3223.9874096327,
        "active":true,
        "build_year":0,
        "lifetime":null,
        "length":76.5646966618,
        "carrier":"AC",
        "terrain_factor":1.0,
        "num_parallel":6.0,
        "v_ang_min":null,
        "v_ang_max":null,
        "sub_network":"",
        "x_pu":0.0,
        "r_pu":0.0,
        "g_pu":0.0,
        "b_pu":0.0,
        "x_pu_eff":0.0000217393,
        "r_pu_eff":0.0000026511,
        "s_nom_opt":10188.6157685126,
        "dc":0.0,
        "i_nom":2.58,
        "v_nom":380.0,
        "id":"74",
        "location0":"DE0 36",
        "location1":"DE0 37",
        "location":null
    },
    "75":{
        "bus0":"DE0 36",
        "bus1":"DE0 5",
        "type":"Al\/St 240\/40 4-bundle 380.0",
        "x":18.4650347773,
        "r":2.2518335094,
        "g":0.0,
        "b":0.0013016792,
        "s_nom":3396.2052234811,
        "s_nom_mod":0.0,
        "s_nom_extendable":true,
        "s_nom_min":3396.2052234811,
        "s_nom_max":23396.2052234811,
        "s_max_pu":0.7,
        "capital_cost":6320.1886175889,
        "active":true,
        "build_year":0,
        "lifetime":null,
        "length":150.1222339622,
        "carrier":"AC",
        "terrain_factor":1.0,
        "num_parallel":2.0,
        "v_ang_min":null,
        "v_ang_max":null,
        "sub_network":"",
        "x_pu":0.0,
        "r_pu":0.0,
        "g_pu":0.0,
        "b_pu":0.0,
        "x_pu_eff":0.0001278742,
        "r_pu_eff":0.0000155944,
        "s_nom_opt":3396.2052799259,
        "dc":0.0,
        "i_nom":2.58,
        "v_nom":380.0,
        "id":"75",
        "location0":"DE0 36",
        "location1":"DE0 5",
        "location":null
    },
    "76":{
        "bus0":"DE0 37",
        "bus1":"DE0 5",
        "type":"Al\/St 240\/40 4-bundle 380.0",
        "x":3.2336317876,
        "r":0.3943453399,
        "g":0.0,
        "b":0.0036472404,
        "s_nom":13584.8208939242,
        "s_nom_mod":0.0,
        "s_nom_extendable":true,
        "s_nom_min":13584.8208939242,
        "s_nom_max":33584.8208939242,
        "s_max_pu":0.7,
        "capital_cost":4428.9587524061,
        "active":true,
        "build_year":0,
        "lifetime":null,
        "length":105.1587573193,
        "carrier":"AC",
        "terrain_factor":1.0,
        "num_parallel":8.0,
        "v_ang_min":null,
        "v_ang_max":null,
        "sub_network":"",
        "x_pu":0.0,
        "r_pu":0.0,
        "g_pu":0.0,
        "b_pu":0.0,
        "x_pu_eff":0.0000223936,
        "r_pu_eff":0.0000027309,
        "s_nom_opt":13584.8217070904,
        "dc":0.0,
        "i_nom":2.58,
        "v_nom":380.0,
        "id":"76",
        "location0":"DE0 37",
        "location1":"DE0 5",
        "location":null
    },
    "8":{
        "bus0":"DE0 1",
        "bus1":"DE0 9",
        "type":"Al\/St 240\/40 4-bundle 380.0",
        "x":8.5241848526,
        "r":1.0395347381,
        "g":0.0,
        "b":0.001352039,
        "s_nom":5094.3078352216,
        "s_nom_mod":0.0,
        "s_nom_extendable":true,
        "s_nom_min":5094.3078352216,
        "s_nom_max":25094.3078352216,
        "s_max_pu":0.7,
        "capital_cost":4377.7533137803,
        "active":true,
        "build_year":0,
        "lifetime":null,
        "length":103.9534738124,
        "carrier":"AC",
        "terrain_factor":1.0,
        "num_parallel":3.0,
        "v_ang_min":null,
        "v_ang_max":null,
        "sub_network":"",
        "x_pu":0.0,
        "r_pu":0.0,
        "g_pu":0.0,
        "b_pu":0.0,
        "x_pu_eff":0.0000590318,
        "r_pu_eff":0.000007199,
        "s_nom_opt":5094.3078753431,
        "dc":0.0,
        "i_nom":2.58,
        "v_nom":380.0,
        "id":"8",
        "location0":"DE0 1",
        "location1":"DE0 9",
        "location":null
    },
    "9":{
        "bus0":"DE0 10",
        "bus1":"DE0 19",
        "type":"Al\/St 240\/40 4-bundle 380.0",
        "x":22.959925125,
        "r":2.7999908689,
        "g":0.0,
        "b":0.0016185433,
        "s_nom":3396.2052234811,
        "s_nom_mod":0.0,
        "s_nom_extendable":true,
        "s_nom_min":3396.2052234811,
        "s_nom_max":23396.2052234811,
        "s_max_pu":0.7,
        "capital_cost":7858.8689005334,
        "active":true,
        "build_year":0,
        "lifetime":null,
        "length":186.6660579267,
        "carrier":"AC",
        "terrain_factor":1.0,
        "num_parallel":2.0,
        "v_ang_min":null,
        "v_ang_max":null,
        "sub_network":"",
        "x_pu":0.0,
        "r_pu":0.0,
        "g_pu":0.0,
        "b_pu":0.0,
        "x_pu_eff":0.0001590023,
        "r_pu_eff":0.0000193905,
        "s_nom_opt":3396.2052384787,
        "dc":0.0,
        "i_nom":2.58,
        "v_nom":380.0,
        "id":"9",
        "location0":"DE0 10",
        "location1":"DE0 19",
        "location":null
    }
}